{
  "data": {
    "consentId": "urn:itau:ITU630607040",
    "creationDateTime": "2021-08-05T12:01:00Z",
    "expirationDateTime": "2021-08-05T13:01:00Z",
    "ibgeTownCode": "4314902",
    "statusUpdateDateTime": "2021-08-05T12:11:00Z",
    "status": "CONSUMED",
    "loggedUser": {
      "document": {
        "identification": "74983393072",
        "rel": "CPF"
      }
    },
    "businessEntity": {
      "document": {
        "identification": "",
        "rel": ""
      }
    },
    "creditor": {
      "personType": "PESSOA_JURIDICA",
      "cpfCnpj": "47960950000121",
      "name": "MAGAZINE LUIZA S/A"
    },
    "payment": {
      "type": "PIX",
      "date": "2021-08-03",
      "currency": "BRL",
      "amount": "1786.45",
      "ibgeTownCode": "4314902",
      "details": {
        "localInstrument": "INIC",
        "qrCode": "69762697669762390229239022939022BR.GOV.BCB.PIX863466756C616E6F3293986393913466756C616E6F3466756C616E6F BR.COM.OUTRO697623902292650579176976239022926505.697623BR6978FATIMA589769690069789787 645544RP58754691-201950300017BR.GOV.BCB.BRCODE01051.0.080450014BR.GOV.BCB.PIX0123PADRAO.URL.PIX/0123AB CD58546477BR.COM.69762390.ABCD.6976.WXYZ5878EB78",
        "proxy": "e561c1e4-3342-482f-8672-7b8f7f4f",
        "creditorAccount": {
          "ispb": "60701190",
          "issuer": "7793",
          "number": "532727",
          "accountType": "CACC"
        }
      }
    },
    "debtorAccount": {
      "ispb": "60746948",
      "issuer": "1360",
      "number": "08297983",
      "accountType": "CACC"
    }
  },
  "links": {
    "self": "https://api.itau/open-banking/payments/v1/consents/urn:itau:ITU630607040"
  },
  "meta": {
    "totalRecords": 1,
    "totalPages": 1,
    "requestDateTime": "2021-08-05T12:11:00Z"
  }
}