{
    "data": [
        {
            "transactionId": "5c91a420-3a42-30ae-af43-1ac25dee9b37",
            "completedAuthorisedPaymentType": "TRANSACAO_EFETIVADA",
            "creditDebitType": "CREDITO",
            "transactionName": "DEP5c91a420-3a42-30ae-af43-1ac25dee9b37",
            "type": "DEPOSITO",
            "amount": 5900.0000,
            "transactionCurrency": "BRL",
            "transactionDate": "2021-06-30",
            "partieCnpjCpf": "64258217018",
            "partiePersonType": "PESSOA_NATURAL",
            "partieCompeCode": "041",
            "partieBranchCode": "5986",
            "partieNumber": "598615",
            "partieCheckDigit": "2"
        },
        {
            "transactionId": "5de9d045-bb19-345f-872d-5d8c5eb91cbb",
            "completedAuthorisedPaymentType": "TRANSACAO_EFETIVADA",
            "creditDebitType": "CREDITO",
            "transactionName": "TED5de9d045-bb19-345f-872d-5d8c5eb91cbb",
            "type": "TED",
            "amount": 1500.0000,
            "transactionCurrency": "BRL",
            "transactionDate": "2021-06-29",
            "partieCnpjCpf": "29750879422",
            "partiePersonType": "PESSOA_NATURAL",
            "partieCompeCode": "341",
            "partieBranchCode": "5658",
            "partieNumber": "456812",
            "partieCheckDigit": "7"
        },        
        {
            "transactionId": "65a6adbb-c8df-3cd0-9a65-e86884ba1e13",
            "completedAuthorisedPaymentType": "TRANSACAO_EFETIVADA",
            "creditDebitType": "DEBITO",
            "transactionName": "SAQ65a6adbb-c8df-3cd0-9a65-e86884ba1e13",
            "type": "SAQUE",
            "amount": 500.0000,
            "transactionCurrency": "BRL",
            "transactionDate": "2021-06-15",
            "partieCnpjCpf": "29750879422",
            "partiePersonType": "PESSOA_NATURAL",
            "partieCompeCode": "001",
            "partieBranchCode": "1235",
            "partieNumber": "2512",
            "partieCheckDigit": "0"
        },
        {
            "transactionId": "fa84e7d4-1c00-36c9-8b55-270d8e6aeea6",
            "completedAuthorisedPaymentType": "TRANSACAO_EFETIVADA",
            "creditDebitType": "CREDITO",
            "transactionName": "PIX para a conta conjunta.",
            "type": "PIX",
            "amount": 8600.0000,
            "transactionCurrency": "BRL",
            "transactionDate": "2021-06-05",
            "partieCnpjCpf": "29750879422",
            "partiePersonType": "PESSOA_NATURAL",
            "partieCompeCode": "341",
            "partieBranchCode": "5658",
            "partieNumber": "456812",
            "partieCheckDigit": "7"
        }
    ],
    "links": {
        "self": "https://openbanking.banrisul.com.br/open-banking/accounts/v1/accounts/be3d308b-d113-3b73-9a95-2b3c87688878/transactions"
    },
    "meta": {
        "totalRecords": 4,
        "totalPages": 1,
        "requestDateTime": "2021-12-26T13:59:00Z"
    }
}