{
    "data": [
        {
            "transactionId": "0bf5258d-4ebf-4bf2-b289-5108a1d30875",
            "completedAuthorisedPaymentType": "TRANSACAO_EFETIVADA",
            "creditDebitType": "DEBITO",
            "transactionName": "PAGAMENTO",
            "type": "CARTAO",
            "transactionAmount": {
                "amount": "39.5200",
                "Currency": "BRL"
            },
            "transactionDate": "2022-08-19",
            "partieCnpjCpf": "30742928497",
            "partiePersonType": "PESSOA_NATURAL",
            "partieCompeCode": "001",
            "partieBranchCode": "6572",
            "partieNumber": "94088092",
            "partieCheckDigit": "3"
        },
        {
            "transactionId": "07f76f7a-d205-44aa-936f-1653a2c5a502",
            "completedAuthorisedPaymentType": "TRANSACAO_EFETIVADA",
            "creditDebitType": "DEBITO",
            "transactionName": "TRANS07f76f7a-d205-44aa-936f-1653a2c5a502",
            "type": "PIX",
            "transactionAmount": {
                "amount": "36.1100",
                "currency": "BRL"
            },
            "transactionDate": "2022-08-25",
            "partieCnpjCpf": "29750879422",
            "partiePersonType": "PESSOA_NATURAL",
            "partieCompeCode": "104",
            "partieBranchCode": "3272",
            "partieNumber": "81290854360",
            "partieCheckDigit": "7"
        }
    ],
    "links": {
        "self": "https://api.caixa.gov.br/open-banking/accounts/v1/accounts/b569dcaf-aef4-44cc-bd84-b12ae26cb16b/transactions"
    },
    "meta": {
        "requestDateTime": "2022-08-24T09:35:00Z"
    }
}