{
    "data": [
        {
            "billId": "bda46855-4ed0-30e7-8add-dbd32985c359",
            "dueDate": "2020-11-10",
            "billTotalAmount": 3943.0496,
            "billTotalAmountCurrency": "BRL",
            "billMinimumAmount": 349.0496,
            "billMinimumAmountCurrency": "BRL",
            "isInstalment": false,
            "financeCharges": [
                {
                    "type": "MULTA_ATRASO_PAGAMENTO_FATURA",
                    "additionalInfo": "Atraso no pagamento da dívida.",
                    "amount": 165.5400,
                    "currency": "BRL"
                },
                {
                    "type": "IOF",
                    "additionalInfo": "IOF",
                    "amount": 45.5400,
                    "currency": "BRL"
                }
            ],
            "payments": [
                {
                    "valueType": "OUTRO_VALOR_PAGO_FATURA",
                    "paymentDate": "2020-12-01",
                    "paymentMode": "DEBITO_CONTA_CORRENTE",
                    "amount": 1574.5626,
                    "currency": "BRL"
                }
            ]
        },
        {
            "billId": "afb47682-1aae-3877-ae3d-f108f4fa7aec",
            "dueDate": "2020-10-10",
            "billTotalAmount": 1320.6417,
            "billTotalAmountCurrency": "BRL",
            "billMinimumAmount": 259.9821,
            "billMinimumAmountCurrency": "BRL",
            "isInstalment": false,
            "financeCharges": [
                {
                    "type": "MULTA_ATRASO_PAGAMENTO_FATURA",
                    "additionalInfo": "NA",
                    "amount": 0.0000,
                    "currency": "BRL"
                }
            ],
            "payments": [
                {
                    "valueType": "VALOR_PAGAMENTO_FATURA_REALIZADO",
                    "paymentDate": "2020-10-10",
                    "paymentMode": "BOLETO_BANCARIO",
                    "amount": 1320.6417,
                    "currency": "BRL"
                }
            ]
        }
    ],
    "links": {
        "self": "https://api.itau/open-banking/credit-cards-accounts/v1/accounts/87684e13-3f03-3c4e-b00a-2b9f2f8215c0/bills"
    },
    "meta": {
        "totalRecords": 2,
        "totalPages": 1,
        "requestDateTime": "2021-06-24T15:28:47Z"
    }
}