{
  "data": {
    "typeNumberOfInstalments": "ANO",
    "totalNumberOfInstalments": 2,
    "typeContractRemaining": "ANO",
    "contractRemainingNumber": 0,
    "paidInstalments": 2,
    "dueInstalments": 0,
    "pastDueInstalments": 0,
    "balloonPayments": [
      {
        "dueDate": "2016-12-01",
        "amount": {
          "amount": "20000.0000",
          "currency": "BRL"
        }
      }
    ]
  },
  "links": {
    "self": "https://api.caixa.gov.br/open-banking/financings/v1/contracts/ef7555e6-d629-33ce-8cf9-ee95e92241a0/scheduled-instalments"
  },
  "meta": {
    "totalRecords": 1,
    "totalPages": 1,
    "requestDateTime": "2022-09-16T11:04:00Z"
  }
}